mpt/__init__.py
mpt/__version__.py
mpt/mpt.py
mpt/cli_scripts/__init__.py
mpt-0.1.0.dist-info/DESCRIPTION.rst
mpt-0.1.0.dist-info/METADATA
mpt-0.1.0.dist-info/RECORD
mpt-0.1.0.dist-info/WHEEL
mpt-0.1.0.dist-info/entry_points.txt
mpt-0.1.0.dist-info/metadata.json
mpt-0.1.0.dist-info/top_level.txt
tests/__init__.py
tests/test_mpt.py
