Metadata-Version: 2.0
Name: mpt
Version: 0.1.0
Summary: Microstructure Protocol Toolbox
Home-page: https://github.com/robbert-harms/MPT
Author: Robbert Harms
Author-email: robbert.harms@maastrichtuniversity.nl
Maintainer: Robbert Harms
Maintainer-email: robbert.harms@maastrichtuniversity.nl
License: LGPL v3
Keywords: mpt
Platform: UNKNOWN
Classifier: Environment :: Console
Classifier: Environment :: X11 Applications :: Qt
Classifier: Intended Audience :: Developers
Classifier: Intended Audience :: Science/Research
Classifier: License :: OSI Approved :: GNU Lesser General Public License v3 or later (LGPLv3+)
Classifier: Development Status :: 5 - Production/Stable
Classifier: Natural Language :: English
Classifier: Operating System :: POSIX :: Linux
Classifier: Operating System :: MacOS :: MacOS X
Classifier: Operating System :: Microsoft :: Windows
Classifier: Programming Language :: Python :: 3
Classifier: Programming Language :: Python :: 3.4
Classifier: Programming Language :: Python :: 3.5
Classifier: Programming Language :: Python :: 3.6
Classifier: Topic :: Scientific/Engineering
Requires-Dist: mdt
